Metadata-Version: 2.1
Name: polska
Version: 1.0
Summary: Пакет для перевода выражения в обратную польскую запись
Home-page: UNKNOWN
Author: Demekhina Arina
Author-email: ademkhina@list.ru
License: UNKNOWN
Platform: UNKNOWN
